kotti_sitemap
