Metadata-Version: 1.0
Name: kotti-sitemap
Version: 0.1.1
Summary: Kotti Sitemap - an addon to easily create a sitemap for your Kotti project.
Home-page: https://github.com/koansys/kotti_sitemap
Author: Koansys, LLC
Author-email: info@koansys.com
License: http://koansys.com/license.txt
Keywords: kotti cms pyramid sitemap sqlalchemy
Platform: UNKNOWN
Classifier: Development Status :: 3 - Alpha
Classifier: Environment :: Web Environment
Classifier: Intended Audience :: Developers
Classifier: Operating System :: OS Independent
Classifier: Programming Language :: Python
Classifier: Framework :: Pyramid
